MANIFEST.in
README.rst
setup.py
auslfe/__init__.py
auslfe.formonline.content.egg-info/PKG-INFO
auslfe.formonline.content.egg-info/SOURCES.txt
auslfe.formonline.content.egg-info/dependency_links.txt
auslfe.formonline.content.egg-info/entry_points.txt
auslfe.formonline.content.egg-info/namespace_packages.txt
auslfe.formonline.content.egg-info/not-zip-safe
auslfe.formonline.content.egg-info/requires.txt
auslfe.formonline.content.egg-info/top_level.txt
auslfe/formonline/__init__.py
auslfe/formonline/content/README.txt
auslfe/formonline/content/__init__.py
auslfe/formonline/content/config.py
auslfe/formonline/content/configure.zcml
auslfe/formonline/content/event.py
auslfe/formonline/content/i18n.sh
auslfe/formonline/content/setuphandlers.py
auslfe/formonline/content/browser/__init__.py
auslfe/formonline/content/browser/configure.zcml
auslfe/formonline/content/browser/viewlet.py
auslfe/formonline/content/browser/workflow_info_viewlet.pt
auslfe/formonline/content/browser/images/downloaddocument.gif
auslfe/formonline/content/content/__init__.py
auslfe/formonline/content/content/configure.zcml
auslfe/formonline/content/content/formonline.py
auslfe/formonline/content/i18n/plone-it.po
auslfe/formonline/content/i18n/plone.pot
auslfe/formonline/content/interfaces/__init__.py
auslfe/formonline/content/interfaces/formonline.py
auslfe/formonline/content/locales/auslfe.formonline.content.pot
auslfe/formonline/content/locales/it/LC_MESSAGES/auslfe.formonline.content.po
auslfe/formonline/content/profiles/default/auslfe.formonline.content_various.txt
auslfe/formonline/content/profiles/default/import_steps.xml
auslfe/formonline/content/profiles/default/metadata.xml
auslfe/formonline/content/profiles/default/workflows.xml
auslfe/formonline/content/profiles/default/workflows/formonline_workflow/definition.xml
auslfe/formonline/content/profiles/default/workflows/formonline_workflow_single_step/definition.xml
auslfe/formonline/content/profiles/withtypes/auslfe.formonline.content_types.txt
auslfe/formonline/content/profiles/withtypes/diff_tool.xml
auslfe/formonline/content/profiles/withtypes/factorytool.xml
auslfe/formonline/content/profiles/withtypes/import_steps.xml
auslfe/formonline/content/profiles/withtypes/metadata.xml
auslfe/formonline/content/profiles/withtypes/propertiestool.xml
auslfe/formonline/content/profiles/withtypes/repositorytool.xml
